{
    "text": "A zero-day vulnerability (CVE-2023-36884) affecting Microsoft Windows and Office products is being exploited by attackers in the wild. To date, the exploit has been used in highly targeted attacks against organizations in the government and defense sectors in Europe and North America. The vulnerability was disclosed yesterday (July 11) by Microsoft, which said that an attacker could create a specially crafted Microsoft Office document that enables remote code execution on the target's computer. In order for the exploit to succeed, the victim needs to open the malicious file. No patch has been released yet for the vulnerability. ",
    "explicit_triplets": [
        {
            "subject": "CVE-2023-36884",
            "relation": "affects",
            "object": "Microsoft Windows"
        },
        {
            "subject": "CVE-2023-36884",
            "relation": "affects",
            "object": "Office products"
        },
        {
            "subject": "attackers",
            "relation": "are exploiting",
            "object": "CVE-2023-36884"
        },
        {
            "subject": "CVE-2023-36884",
            "relation": "used in attacks against",
            "object": "organizations in the government and defense sectors in Europe"
        },
        {
            "subject": "CVE-2023-36884",
            "relation": "used in attacks against",
            "object": "organizations in the government and defense sectors in North America"
        },
        {
            "subject": "Microsoft",
            "relation": "disclosed",
            "object": "CVE-2023-36884"
        },
        {
            "subject": "Microsoft",
            "relation": "disclosed CVE-2023-36884 on",
            "object": "July 11"
        },
        {
            "subject": "attacker",
            "relation": "could create",
            "object": "specially crafted Microsoft Office document"
        },
        {
            "subject": "specially crafted Microsoft Office document",
            "relation": "enables",
            "object": "remote code execution"
        }
    ],
    "entities": [
        {
            "entity_id": 0,
            "entity_name": "CVE-2023-36884",
            "entity_type": "Vulnerability",
            "mentions": []
        },
        {
            "entity_id": 1,
            "entity_name": "Microsoft Windows",
            "entity_type": "Infrastructure",
            "mentions": []
        },
        {
            "entity_id": 2,
            "entity_name": "Office products",
            "entity_type": "Infrastructure",
            "mentions": []
        },
        {
            "entity_id": 4,
            "entity_name": "organizations in the government and defense sectors in Europe",
            "entity_type": "Organization",
            "mentions": []
        },
        {
            "entity_id": 5,
            "entity_name": "organizations in the government and defense sectors in North America",
            "entity_type": "Organization",
            "mentions": []
        },
        {
            "entity_id": 6,
            "entity_name": "Microsoft",
            "entity_type": "Organization",
            "mentions": []
        },
        {
            "entity_id": 7,
            "entity_name": "July 11",
            "entity_type": "Time",
            "mentions": []
        },
        {
            "entity_id": 3,
            "entity_name": "attacker",
            "entity_type": "Attacker",
            "mentions": [
                "attackers"
            ]
        },
        {
            "entity_id": 8,
            "entity_name": "specially crafted Microsoft Office document",
            "entity_type": "Indicator:File",
            "mentions": []
        },
        {
            "entity_id": 9,
            "entity_name": "remote code execution",
            "entity_type": "Malware Characteristic:Capability",
            "mentions": []
        }
    ],
    "implicit_triplets": []
}
